dms_variant/__init__.py
dms_variant/mutation.py
dms_variant/variant.py
dms_variant-0.1.0.dist-info/LICENSE
dms_variant-0.1.0.dist-info/METADATA
dms_variant-0.1.0.dist-info/WHEEL
dms_variant-0.1.0.dist-info/RECORD
