Metadata-Version: 2.3
Name: dms-variant
Version: 0.1.0
Summary: Lightweight parser of single- and multi-mutation variants in DMS experiment results
License: MIT
Author: Jingyou Rao
Author-email: roseraosh@gmail.com
Requires-Python: >=3.10
Classifier: License :: OSI Approved :: MIT License
Classifier: Programming Language :: Python :: 3
Classifier: Programming Language :: Python :: 3.10
Classifier: Programming Language :: Python :: 3.11
Classifier: Programming Language :: Python :: 3.12
Classifier: Programming Language :: Python :: 3.13
